macwinnie_sqlite3/SQLite.py
macwinnie_sqlite3/__init__.py
macwinnie_sqlite3-1.0.2.dist-info/LICENSE
macwinnie_sqlite3-1.0.2.dist-info/METADATA
macwinnie_sqlite3-1.0.2.dist-info/WHEEL
macwinnie_sqlite3-1.0.2.dist-info/top_level.txt
macwinnie_sqlite3-1.0.2.dist-info/RECORD
